Metadata-Version: 2.1
Name: hydrogapai
Version: 0.6.0
Summary: HydroGAP-AI: Hydro-Gap Artificial Intelligence
Home-page: https://github.com/kperi/HydroGAP-AI
Author: Konstantinos Perifanos, Yiannis Kontons, Konstantinos Plataridis
Author-email: kostas.perifanos@gmail.com, ykontos81@gmail.com, platarid@gmail.com
Classifier: Development Status :: 3 - Alpha
Classifier: Intended Audience :: Science/Research
Classifier: License :: OSI Approved :: MIT License
Classifier: Operating System :: OS Independent
Classifier: Programming Language :: Python :: 3
Classifier: Programming Language :: Python :: 3.8
Classifier: Programming Language :: Python :: 3.9
Classifier: Programming Language :: Python :: 3.10
Classifier: Programming Language :: Python :: 3.11
Classifier: Programming Language :: Python :: 3.12
Requires-Python: >=3.8
License-File: LICENSE
